Master_controller/Master_controller.v

`default_nettype none
module Master_controller(
    input wire BaudRate,            // From baud rate generator
    input wire rst,                 // Global Reset
    input wire SS,                  // Slave Select , active low, comes from processor or port register
    input wire SPE,                 // SPI enable from SPCR, comes from user
    input wire MSTR,                // Master enable from SPCR, comes from user
    output reg Reg_write_en,       // enable writing in SPI Status Register(SPSR) , to enable writing SPIF
    output reg Shifter_en,         // enable shifter operation 
    output reg idle,               // signal indicates that nothing is being sent/recieved, goes to SCK_control,when idle state , idle =1
    output wire M_BaudRate,          // Master baud rate, goes to SCK control
    output reg SPIF,                // SPI Flag, is set to high when 1 byte is ready and written to SPDR
    output wire BRG_clr,            // is set to 1 when SS is 1 or MSTR is 0, goes to BRG
    output reg SPDR_wr_en,          // goes to shifter to enable writing to SPDR from shifter register
    output reg SPDR_rd_en           // goes to shifter to enable writing to shifter register after reading SPDR
);
    localparam Idle = 0 , Run = 1, Update = 2;
    reg [1:0] current_state, next_state;
    assign M_BaudRate = ~idle & ~BaudRate;
   
    reg [2:0] counter;
    reg  counter_enable ; 
    always@(posedge BaudRate or negedge rst)
    begin
        if(!rst) begin counter<='b0; end

        else if (counter_enable)
        begin 
            counter <= counter + 1'b1;
        end
    end

    assign BRG_clr = ~MSTR | SS | ~SPE;


    always @(posedge BaudRate , negedge rst) begin
        if(~rst)
            current_state <= Idle;
        else
            current_state <= next_state;
    end

    always @(*) 
        case (current_state)
            Idle:   if (!SS && MSTR && SPE) begin next_state=Run; end
                    else begin next_state=Idle; end
            
            Run:    if (counter==7) begin next_state=Update; end
                    else begin next_state=Run; end

            Update: next_state=Idle;
        endcase 


    always @(*) begin
        idle = 0;
        SPDR_rd_en = 0;
        SPDR_wr_en = 0;
        Shifter_en = 0;
        SPIF = 0;
        Reg_write_en = 0;
        counter_enable = 0;
        case (current_state)
            Idle :  begin
                        idle = 1;
                        SPDR_rd_en = 1;
                    end
            Run :   begin
                        Shifter_en = 1; 
                        counter_enable = 1;
                    end
            Update: begin
                        idle = 1; 
                        SPDR_wr_en = 1;
                        SPIF = 1;
                        Reg_write_en = 1;
                    end
            
        endcase
    end


endmodule

Master_controller/Master_controller_TB.v
`default_nettype none
`timescale 1ns/100ps
`include "Master_controller.v"

module Master_controller_TB;
    reg BaudRate = 0, rst, SS, SPE,MSTR;
    wire M_BaudRate, Reg_write_en, Shifter_en, idle, SPIF, BRG_clr, SPDR_wr_en, SPDR_rd_en;

    Master_controller inst1(
        .BaudRate(BaudRate),
        .rst(rst),
        .SS(SS),
        .SPE(SPE),
        .MSTR(MSTR),
        .Reg_write_en(Reg_write_en),
        .Shifter_en(Shifter_en),
        .idle(idle),
        .SPIF(SPIF),
        .M_BaudRate(M_BaudRate),
        .BRG_clr(BRG_clr),
        .SPDR_wr_en(SPDR_wr_en),
        .SPDR_rd_en(SPDR_rd_en)
    );

    always BaudRate = #2 ~BaudRate;

    initial begin
        $dumpfile("dump.vcd");
        $dumpvars;
        rst = 0; #3 rst = 1; SS = 0; SPE = 1; MSTR = 0;
        #5;
        MSTR = 1;
        #40;
        $finish;
    end



endmodule

Master_controller/dump.vcd
$date
	Sat Jul 22 14:58:30 2023
$end
$version
	Icarus Verilog
$end
$timescale
	100ps
$end
$scope module Master_controller_TB $end
$var wire 1 ! idle $end
$var wire 1 " Shifter_en $end
$var wire 1 # SPIF $end
$var wire 1 $ SPDR_wr_en $end
$var wire 1 % SPDR_rd_en $end
$var wire 1 & Reg_write_en $end
$var wire 1 ' M_BaudRate $end
$var wire 1 ( BRG_clr $end
$var reg 1 ) BaudRate $end
$var reg 1 * MSTR $end
$var reg 1 + SPE $end
$var reg 1 , SS $end
$var reg 1 - rst $end
$scope module inst1 $end
$var wire 1 ( BRG_clr $end
$var wire 1 ) BaudRate $end
$var wire 1 * MSTR $end
$var wire 1 ' M_BaudRate $end
$var wire 1 + SPE $end
$var wire 1 , SS $end
$var wire 1 - rst $end
$var parameter 32 . Idle $end
$var parameter 32 / Run $end
$var parameter 32 0 Update $end
$var reg 1 & Reg_write_en $end
$var reg 1 % SPDR_rd_en $end
$var reg 1 $ SPDR_wr_en $end
$var reg 1 # SPIF $end
$var reg 1 " Shifter_en $end
$var reg 3 1 counter [2:0] $end
$var reg 1 2 counter_enable $end
$var reg 2 3 current_state [1:0] $end
$var reg 1 ! idle $end
$var reg 2 4 next_state [1:0] $end
$upscope $end
$upscope $end
$enddefinitions $end
$comment Show the parameter values. $end
$dumpall
b10 0
b1 /
b0 .
$end
#0
$dumpvars
b0 4
b0 3
02
b0 1
0-
x,
x+
x*
0)
x(
0'
0&
1%
0$
0#
0"
1!
$end
#20
1)
#30
1(
0*
1+
0,
1-
#40
0)
#60
1)
#80
0(
b1 4
0)
1*
#100
12
1"
0%
0!
b1 3
1)
#120
1'
0)
#140
b1 1
0'
1)
#160
1'
0)
#180
b10 1
0'
1)
#200
1'
0)
#220
b11 1
0'
1)
#240
1'
0)
#260
b100 1
0'
1)
#280
1'
0)
#300
b101 1
0'
1)
#320
1'
0)
#340
b110 1
0'
1)
#360
1'
0)
#380
b10 4
b111 1
0'
1)
#400
1'
0)
#420
1&
1#
1$
1!
02
0"
b0 4
b10 3
b0 1
0'
1)
#440
0)
#460
1%
0&
0#
0$
1!
b1 4
b0 3
1)
#480
0)
