BRG/BRG.v
`default_nettype none

module BRG
#(  parameter PrescalarWidth = 3)
(
    input wire clk,
    input wire rst, // ~rst | SS
    input wire clr,
    input wire [PrescalarWidth-1:0] SPR,
    input wire en, // ~SS & MSTR & SPE
    output wire BaudRate
);

    reg [2**PrescalarWidth-1:0] counter;
    wire [2**PrescalarWidth-1:0] counterNext;
    

    always @(posedge clk or negedge rst) begin
        if(~rst | clr)
            counter <= 0;
        else begin
            if (en) begin
                counter <= counterNext;
            end
        end 
    end
    assign counterNext = counter + 1;
    assign BaudRate = counter[SPR];

endmodule

BaudRateGenerator/BRG_TB.v
`default_nettype none
`timescale 1ns/100ps
`include "BRG.v"

module BRG_TB;

    localparam PrescalarWidth = 3;
    localparam ClockPeriod = 10;

    reg clk = 0,rst = 0,en = 0, clr=1;
    reg [PrescalarWidth-1:0] SPR = 0;
    wire BaudRate;

    always #(ClockPeriod/2) clk = ~clk;
    
    BRG BRG_inst(.clk(clk), .rst(rst), .clr(clr), .en(en), .SPR(SPR), .BaudRate(BaudRate));

    initial begin
        $dumpfile("dump.vcd");
        $dumpvars;
        #15
        rst = 1; en = 1; clr = 0;
        #200
        SPR = 1;
        #200
        SPR = 2; en = 1; clr = 1;
        #200
        SPR = 1;
        #100 $finish;
    end

endmodule

BRG/dump.vcd
$date
	Sat Jul 22 07:39:01 2023
$end
$version
	Icarus Verilog
$end
$timescale
	100ps
$end
$scope module BRG_TB $end
$var wire 1 ! BaudRate $end
$var parameter 32 " ClockPeriod $end
$var parameter 32 # PrescalarWidth $end
$var reg 3 $ SPR [2:0] $end
$var reg 1 % clk $end
$var reg 1 & clr $end
$var reg 1 ' en $end
$var reg 1 ( rst $end
$scope module BRG_inst $end
$var wire 3 ) SPR [2:0] $end
$var wire 1 % clk $end
$var wire 1 & clr $end
$var wire 1 ' en $end
$var wire 1 ( rst $end
$var wire 8 * counterNext [7:0] $end
$var wire 1 ! BaudRate $end
$var parameter 32 + PrescalarWidth $end
$var reg 8 , counter [7:0] $end
$upscope $end
$upscope $end
$enddefinitions $end
$comment Show the parameter values. $end
$dumpall
b11 +
b11 #
b1010 "
$end
#0
$dumpvars
b0 ,
b1 *
b0 )
0(
0'
1&
0%
b0 $
0!
$end
#50
1%
#100
0%
#150
b10 *
1!
b1 ,
1%
0&
1'
1(
#200
0%
#250
b11 *
0!
b10 ,
1%
#300
0%
#350
b100 *
1!
b11 ,
1%
#400
0%
#450
b101 *
0!
b100 ,
1%
#500
0%
#550
b110 *
1!
b101 ,
1%
#600
0%
#650
b111 *
0!
b110 ,
1%
#700
0%
#750
b1000 *
1!
b111 ,
1%
#800
0%
#850
b1001 *
0!
b1000 ,
1%
#900
0%
#950
b1010 *
1!
b1001 ,
1%
#1000
0%
#1050
b1011 *
0!
b1010 ,
1%
#1100
0%
#1150
b1100 *
1!
b1011 ,
1%
#1200
0%
#1250
b1101 *
0!
b1100 ,
1%
#1300
0%
#1350
b1110 *
1!
b1101 ,
1%
#1400
0%
#1450
b1111 *
0!
b1110 ,
1%
#1500
0%
#1550
b10000 *
1!
b1111 ,
1%
#1600
0%
#1650
b10001 *
0!
b10000 ,
1%
#1700
0%
#1750
b10010 *
1!
b10001 ,
1%
#1800
0%
#1850
b10011 *
0!
b10010 ,
1%
#1900
0%
#1950
b10100 *
1!
b10011 ,
1%
#2000
0%
#2050
b10101 *
0!
b10100 ,
1%
#2100
0%
#2150
b10110 *
b10101 ,
1%
b1 $
b1 )
#2200
0%
#2250
b10111 *
1!
b10110 ,
1%
#2300
0%
#2350
b11000 *
b10111 ,
1%
#2400
0%
#2450
b11001 *
0!
b11000 ,
1%
#2500
0%
#2550
b11010 *
b11001 ,
1%
#2600
0%
#2650
b11011 *
1!
b11010 ,
1%
#2700
0%
#2750
b11100 *
b11011 ,
1%
#2800
0%
#2850
b11101 *
0!
b11100 ,
1%
#2900
0%
#2950
b11110 *
b11101 ,
1%
#3000
0%
#3050
b11111 *
1!
b11110 ,
1%
#3100
0%
#3150
b100000 *
b11111 ,
1%
#3200
0%
#3250
b100001 *
0!
b100000 ,
1%
#3300
0%
#3350
b100010 *
b100001 ,
1%
#3400
0%
#3450
b100011 *
1!
b100010 ,
1%
#3500
0%
#3550
b100100 *
b100011 ,
1%
#3600
0%
#3650
b100101 *
0!
b100100 ,
1%
#3700
0%
#3750
b100110 *
b100101 ,
1%
#3800
0%
#3850
b100111 *
1!
b100110 ,
1%
#3900
0%
#3950
b101000 *
b100111 ,
1%
#4000
0%
#4050
b101001 *
0!
b101000 ,
1%
#4100
0%
#4150
b1 *
b0 ,
1%
1&
b10 $
b10 )
#4200
0%
#4250
1%
#4300
0%
#4350
1%
#4400
0%
#4450
1%
#4500
0%
#4550
1%
#4600
0%
#4650
1%
#4700
0%
#4750
1%
#4800
0%
#4850
1%
#4900
0%
#4950
1%
#5000
0%
#5050
1%
#5100
0%
#5150
1%
#5200
0%
#5250
1%
#5300
0%
#5350
1%
#5400
0%
#5450
1%
#5500
0%
#5550
1%
#5600
0%
#5650
1%
#5700
0%
#5750
1%
#5800
0%
#5850
1%
#5900
0%
#5950
1%
#6000
0%
#6050
1%
#6100
0%
#6150
1%
b1 $
b1 )
