Shifter/Shifter.v

`default_nettype none
module Shifter #(parameter DWIDTH = 8)(
    input wire Sample_clk, // to take input from data in (from slave)
    input wire Shift_clk, // shifting inside shifter and to data out
    input wire Data_in,
    input wire shifter_en, //in shift clk block it should be one to shift (coming from controller)
    input wire SPDR_wr_en, // to write in spdr
    input wire SPDR_rd_en, // to read in spdr
    input wire [DWIDTH-1:0] SPDR_in,
    output reg [DWIDTH-1:0] SPDR_out,
    output reg Data_out
);
    reg [DWIDTH-1:0] shifter_data_reg;
    reg [DWIDTH-1:0] shifter_data;

    always@(posedge Sample_clk) begin
        shifter_data_reg <= {shifter_data_reg[DWIDTH-2:0] ,Data_in};
    end


    always@(posedge Shift_clk) begin
        if(shifter_en) begin
            Data_out <= shifter_data_reg[DWIDTH-1];  
        end
    end


    always@(*) begin
        if (SPDR_wr_en) begin
            SPDR_out = shifter_data ;
            shifter_data = shifter_data_reg;
        end
        else if (SPDR_rd_en) begin
            shifter_data_reg = SPDR_in;
            shifter_data = SPDR_in;
            SPDR_out = 'bz ;
        end
        else begin
            shifter_data = shifter_data_reg;
            SPDR_out = 'bz ;
        end
    end


endmodule

SCK_control/SCK_control.v
`default_nettype none
module SCK_control(
    input wire M_BaudRate,
    input wire CPOL,
    input wire CPHA,
    input wire idle, 
    output reg SCK_out,
    output reg Shift_clk,
    output reg Sample_clk
);

always @(*) begin
    Shift_clk = !idle & !M_BaudRate;
    Sample_clk = M_BaudRate;
    case({CPOL, CPHA})
    0: SCK_out = M_BaudRate;
    1: SCK_out = !idle & !M_BaudRate;
    2: SCK_out = !M_BaudRate;
    3: SCK_out = idle | M_BaudRate;
    endcase
end

endmodule

Shifter/Shifter_TB.v
`default_nettype none
`timescale 1ns/100ps
`include "Shifter.v"
`include "../SCK_control/SCK_control.v"
module Shifter_TB();

reg M_BaudRate, CPOL, CPHA, idle;
wire SCK_out, Shift_clk, Sample_clk;
SCK_control sck1(.M_BaudRate(M_BaudRate), .CPOL(CPOL), .CPHA(CPHA), .idle(idle), .SCK_out(SCK_out), .Shift_clk(Shift_clk), .Sample_clk(Sample_clk));

wire Data_out, SPDR_rd_en , shifter_en;
reg SPDR_wr_en, Data_in;
reg [7:0] SPDR_in;
wire [7:0] SPDR_out;

Shifter #(8) shift_inst1(.Sample_clk(Sample_clk), .Shift_clk(Shift_clk), .Data_in(Data_in),.shifter_en(shifter_en), 
    .SPDR_wr_en(SPDR_wr_en), .SPDR_rd_en(SPDR_rd_en), .SPDR_in(SPDR_in), .SPDR_out(SPDR_out), .Data_out(Data_out));

assign shifter_en = 1;
assign SPDR_rd_en = idle;

initial begin
    $dumpfile("dump.vcd");
    $dumpvars;

    // Mode 0 test
    CPOL = 0; CPHA = 1; idle = 1; M_BaudRate = 0; Data_in = 0; SPDR_wr_en = 0; SPDR_in = 8'hFF;
    #5 idle = 0; 
    repeat(8) begin
      M_BaudRate = 0; 
      #1 M_BaudRate = 1;
      #1;
    end
      SPDR_wr_en = 1; 
      #5;

end

endmodule

Shifter/dump.vcd
$date
	Sat Jul 22 14:24:14 2023
$end
$version
	Icarus Verilog
$end
$timescale
	100ps
$end
$scope module Shifter_TB $end
$var wire 1 ! SPDR_rd_en $end
$var wire 1 " shifter_en $end
$var wire 1 # Shift_clk $end
$var wire 1 $ Sample_clk $end
$var wire 8 % SPDR_out [7:0] $end
$var wire 1 & SCK_out $end
$var wire 1 ' Data_out $end
$var reg 1 ( CPHA $end
$var reg 1 ) CPOL $end
$var reg 1 * Data_in $end
$var reg 1 + M_BaudRate $end
$var reg 8 , SPDR_in [7:0] $end
$var reg 1 - SPDR_wr_en $end
$var reg 1 . idle $end
$scope module sck1 $end
$var wire 1 ( CPHA $end
$var wire 1 ) CPOL $end
$var wire 1 + M_BaudRate $end
$var wire 1 . idle $end
$var reg 1 & SCK_out $end
$var reg 1 $ Sample_clk $end
$var reg 1 # Shift_clk $end
$upscope $end
$scope module shift_inst1 $end
$var wire 1 * Data_in $end
$var wire 8 / SPDR_in [7:0] $end
$var wire 1 ! SPDR_rd_en $end
$var wire 1 - SPDR_wr_en $end
$var wire 1 $ Sample_clk $end
$var wire 1 # Shift_clk $end
$var wire 1 " shifter_en $end
$var parameter 32 0 DWIDTH $end
$var reg 1 ' Data_out $end
$var reg 8 1 SPDR_out [7:0] $end
$var reg 8 2 shifter_data [7:0] $end
$var reg 8 3 shifter_data_reg [7:0] $end
$upscope $end
$upscope $end
$enddefinitions $end
$comment Show the parameter values. $end
$dumpall
b1000 0
$end
#0
$dumpvars
b11111111 3
b11111111 2
bz 1
b11111111 /
1.
0-
b11111111 ,
0+
0*
0)
1(
x'
0&
bz %
0$
0#
1"
1!
$end
#50
1'
1&
1#
0!
0.
#60
b11111110 2
b11111110 3
0&
1$
0#
1+
#70
1&
0$
1#
0+
#80
b11111100 2
b11111100 3
0&
1$
0#
1+
#90
1&
0$
1#
0+
#100
b11111000 2
b11111000 3
0&
1$
0#
1+
#110
1&
0$
1#
0+
#120
b11110000 2
b11110000 3
0&
1$
0#
1+
#130
1&
0$
1#
0+
#140
b11100000 2
b11100000 3
0&
1$
0#
1+
#150
1&
0$
1#
0+
#160
b11000000 2
b11000000 3
0&
1$
0#
1+
#170
1&
0$
1#
0+
#180
b10000000 2
b10000000 3
0&
1$
0#
1+
#190
1&
0$
1#
0+
#200
b0 2
b0 3
0&
1$
0#
1+
#210
b0 %
b0 1
1-
