Registers/SPDR.v
`default_nettype none
module SPDR(
    input wire [7:0] SPDR_in,
    input wire [7:0] SPDR_From_user,
    input wire clk, rst, en, SPDR_rd_en,
    output wire [7:0] SPDR_out
);
    reg [7:0] SPDR;
    assign SPDR_out = SPDR;
always @(posedge clk, negedge rst) begin
    if(~rst)
        SPDR <= 0;
    else begin
      if(en)
        SPDR <= SPDR_in;
      else if (SPDR_rd_en)
        SPDR <= SPDR_From_user;
      else
        SPDR <= SPDR_out;
    end
        
end
    

endmodule

Registers/SPIBR.v
module SPIBR(
    input wire [7:0] SPIBR_in,
    input wire clk, rst,
    output wire [2:0] SPR
    );
reg SPR0, SPR1, SPR2;

always @(posedge clk or negedge rst) begin
    if(~rst)begin
      SPR0 <= 0; SPR1 <= 1; SPR2 <= 2;
    end
    else begin
      SPR0 <= SPIBR_in[0];
      SPR1 <= SPIBR_in[1];
      SPR2 <= SPIBR_in[2];
    end
end

assign SPR={SPR2,SPR1,SPR0 };
endmodule

Registers/SPISR.v
`default_nettype none

module SPISR(
    input wire clk, rst, en, 
    input wire SPISR_in,
    output reg SPIF
);

always @(posedge clk or negedge rst) begin
    if(~rst)begin
      SPIF <= 0;
    end
    else begin
        if(en) begin
          SPIF <= SPISR_in;
        end
        else begin
          SPIF <= SPIF;
        end
      
    end
end
endmodule

Registers/SPCR.v
`default_nettype none

module SPCR(
    input wire [7:0] SPCR_in,
    input wire clk, rst,
    output reg SPE, MSTR, CPOL, CPHA, LSBFE
);

always @(posedge clk or negedge rst) begin
    if(~rst)begin
      SPE <= 0; MSTR <= 0; CPOL <= 0; CPHA <= 0; LSBFE <= 0;
    end
    else begin
      SPE <= SPCR_in[6]; //SPI enable
      MSTR <= SPCR_in[4]; // Master or slave
      CPOL <= SPCR_in[3]; //Clock polarity
      CPHA <= SPCR_in[2]; //Clock phase
      LSBFE <= SPCR_in[0]; //Most sig bit or least sig bit first
    end
end
endmodule

SCK_control/SCK_control.v
`default_nettype none
module SCK_control(
    input wire M_BaudRate,
    input wire CPOL,
    input wire CPHA,
    input wire idle, 
    output reg SCK_out,
    output reg Shift_clk,
    output reg Sample_clk
);

always @(*) begin
    Shift_clk = !idle & !M_BaudRate;
    Sample_clk = M_BaudRate;
    case({CPOL, CPHA})
    0: SCK_out = M_BaudRate;
    1: SCK_out = !idle & !M_BaudRate;
    2: SCK_out = !M_BaudRate;
    3: SCK_out = idle | M_BaudRate;
    endcase
end

endmodule

Port_control_logic/Port_control_logic.v
`default_nettype none
module Port_control_logic(
    /*MSTR — SPI Master/Slave Mode Select Bit
                     This bit selects, if the SPI operates in master or slave mode. Switching the SPI from master to slave or
                     vice versa forces the SPI system into idle state.
                     1 = SPI is in Master mode
                     0 = SPI is in Slave mode */
    input wire MSTR, 
    input wire  SCK_out,
    input wire  Data_out,
    input wire  SS_master, //! from processor
    inout wire  MOSI,
    inout wire  MISO,
    inout wire  SCK,
    inout wire  SS,
    output wire SS_slave,  //! it will be driven in case Slave only
    output wire SCK_in,
    output wire Data_in
);


//----------------------------------------------------------------------------------------------------
/*This pin is used to transmit data out of the SPI module when it is configured as a Master and receive data
  when it is configured as Slave.*/
assign  MOSI = MSTR? Data_out: 'bz;
assign  Data_in = MSTR ? MISO : MOSI;
//----------------------------------------------------------------------------------------------------
/*This pin is used to transmit data out of the SPI module when it is configured as a Slave and receive data
when it is configured as Master.*/
assign  MISO = ~MSTR ? Data_out:'bz;
//assign  Data_out= MSTR ? MOSI : MISO;
//----------------------------------------------------------------------------------------------------
/*This pin is used to output the select signal from the SPI module to another peripheral with which a data
transfer is to take place when its configured as a Masterand its used as an input to receive the slave select
signal when the SPI is configured as Slave.*/
assign  SS = MSTR ? SS_master : 'bz;
assign SS_slave = MSTR ? 'bz : SS;
//assign  Data_out= MSTR ? 'bz : SS;
//----------------------------------------------------------------------------------------------------
/*This pin is used to output the clock with respect to which the SPI transfers data or receive clock in case of
Slave.*/
assign  SCK = MSTR ? SCK_out :'bz;
assign  SCK_in = MSTR ? 'bz : SCK;

endmodule

Master_controller/Master_controller.v

`default_nettype none
module Master_controller(
    input wire BaudRate,            // From baud rate generator
    input wire rst,                 // Global Reset
    input wire SS,                  // Slave Select , active low, comes from processor or port register
    input wire SPE,                 // SPI enable from SPCR, comes from user
    input wire MSTR,                // Master enable from SPCR, comes from user
    output reg Reg_write_en,       // enable writing in SPI Status Register(SPSR) , to enable writing SPIF
    output reg Shifter_en,         // enable shifter operation 
    output reg idle,               // signal indicates that nothing is being sent/recieved, goes to SCK_control,when idle state , idle =1
    output wire M_BaudRate,          // Master baud rate, goes to SCK control
    output reg SPIF,                // SPI Flag, is set to high when 1 byte is ready and written to SPDR
    output wire BRG_clr,            // is set to 1 when SS is 1 or MSTR is 0, goes to BRG
    output reg SPDR_wr_en,          // goes to shifter to enable writing to SPDR from shifter register
    output reg SPDR_rd_en           // goes to shifter to enable writing to shifter register after reading SPDR
);
    localparam Idle = 0 , Run = 1, Update = 2;
    reg [1:0] current_state, next_state;
    assign M_BaudRate = ~idle & ~BaudRate;
   
    reg [2:0] counter;
    reg  counter_enable ; 
    always@(posedge BaudRate or negedge rst)
    begin
        if(!rst) begin counter<='b0; end

        else if (counter_enable)
        begin 
            counter <= counter + 1'b1;
        end
    end

    assign BRG_clr = ~MSTR | SS | ~SPE;


    always @(posedge BaudRate , negedge rst) begin
        if(~rst)
            current_state <= Idle;
        else
            current_state <= next_state;
    end

    always @(*) 
        case (current_state)
            Idle:   if (!SS && MSTR && SPE) begin next_state=Run; end
                    else begin next_state=Idle; end
            
            Run:    if (counter==7) begin next_state=Update; end
                    else begin next_state=Run; end

            Update: next_state=Idle;
        endcase 


    always @(*) begin
        idle = 0;
        SPDR_rd_en = 0;
        SPDR_wr_en = 0;
        Shifter_en = 0;
        SPIF = 0;
        Reg_write_en = 0;
        counter_enable = 0;
        case (current_state)
            Idle :  begin
                        idle = 1;
                        SPDR_rd_en = 1;
                    end
            Run :   begin
                        Shifter_en = 1; 
                        counter_enable = 1;
                    end
            Update: begin
                        idle = 1; 
                        SPDR_wr_en = 1;
                        SPIF = 1;
                        Reg_write_en = 1;
                    end
            
        endcase
    end


endmodule

Shifter/Shifter.v

`default_nettype none
module Shifter #(parameter DWIDTH = 8)(
    input wire Sample_clk, // to take input from data in (from slave)
    input wire Shift_clk, // shifting inside shifter and to data out
    input wire Data_in,
    input wire shifter_en, //in shift clk block it should be one to shift (coming from controller)
    input wire SPDR_wr_en, // to write in spdr
    input wire SPDR_rd_en, // to read in spdr
    input wire [DWIDTH-1:0] SPDR_in,
    output reg [DWIDTH-1:0] SPDR_out,
    output reg Data_out
);
    reg [DWIDTH-1:0] shifter_data_reg;
    reg [DWIDTH-1:0] shifter_data;

    always@(posedge Sample_clk) begin
        shifter_data_reg <= {shifter_data_reg[DWIDTH-2:0] ,Data_in};
    end


    always@(posedge Shift_clk) begin
        if(shifter_en) begin
            Data_out <= shifter_data_reg[DWIDTH-1];  
        end
    end


    always@(*) begin
        if (SPDR_wr_en) begin
            SPDR_out = shifter_data ;
            shifter_data = shifter_data_reg;
        end
        else if (SPDR_rd_en) begin
            shifter_data_reg = SPDR_in;
            shifter_data = SPDR_in;
            SPDR_out = 'bz ;
        end
        else begin
            shifter_data = shifter_data_reg;
            SPDR_out = 'bz ;
        end
    end


endmodule

BRG/BRG.v
`default_nettype none

module BRG
#(  parameter PrescalarWidth = 3)
(
    input wire clk,
    input wire rst, // ~rst | SS
    input wire clr,
    input wire [PrescalarWidth-1:0] SPR,
    output wire BaudRate
);

    reg [2**PrescalarWidth-1:0] counter;
    wire [2**PrescalarWidth-1:0] counterNext;
    

    always @(posedge clk or negedge rst) begin
        if(~rst )
            counter <= 0;
        else if(clr)
             counter <= 0;
        else 
          counter <= counterNext;
  
    end

    assign counterNext = counter + 1;
    assign BaudRate = counter[SPR];

endmodule

TestBench/SPI_TOP.v
`default_nettype none
`include "../BRG/BRG.v"
`include "../Master_controller/Master_controller.v"
`include "../Port_control_logic\Port_control_logic.v"
`include "../Registers\SPCR.v"
`include "../Registers\SPDR.v"
`include "../Registers\SPIBR.v"
`include "../Registers\SPISR.v"
`include "../SCK_control\SCK_control.v"
`include "../Shifter\Shifter.v"
module SPI_TOP #(
    parameter PrescalarWidth = 3
) (
    input  wire        rst,
    inout  wire        SS,
    inout  wire        MOSI,
    inout  wire        MISO,
    inout  wire        SCK,
    input  wire        clk,
    input  wire        SS_master,
    output wire        SS_slave,  //!connected to slave control
    output wire        SCK_in, 
    input  wire [7:0]  SPCR_in,
    input  wire        LSBFE,
    output  wire        SPIF,
    input  wire [7:0]  SPIBR_in,
    input  wire [7:0]  SPDR_From_user

);
  
wire               BaudRate;
wire               BRG_clr;
wire    [2:0]      SPR;
wire               Sample_clk;
wire               Shift_clk;
wire               Data_in;
wire               shifter_en;
wire               SPDR_wr_en;
wire               SPDR_rd_en;
wire    [7:0]      SPDR_in;
wire    [7:0]      SPDR_out;
wire               Data_out;
wire               SPE;
wire               MSTR;
wire               Reg_write_en;
wire               idle;
wire               SPISR_in;
wire               SCK_out;
wire               CPHA;
wire               CPOL;
wire               M_BaudRate;

//______________________________________________________________________________

BRG #(
       .PrescalarWidth (PrescalarWidth )
)
u_BRG(
	.clk      (clk      ),
    .rst      (rst      ),
    .clr      (BRG_clr  ),
    .SPR      (SPR      ),
    .BaudRate (BaudRate )
);

//______________________________________________________________________________

Shifter u_Shifter(
	.Sample_clk (Sample_clk ),
   .Shift_clk  (Shift_clk  ),
   .Data_in    (Data_in    ),
   .shifter_en (shifter_en ),
   .SPDR_wr_en (SPDR_wr_en ),
   .SPDR_rd_en (SPDR_rd_en ),
   .SPDR_in    (SPDR_in    ),
   .SPDR_out   (SPDR_out   ),
   .Data_out   (Data_out   )
);

//______________________________________________________________________________

Master_controller u_Master_controller(
    .BaudRate     (BaudRate     ),
    .rst          (rst          ),
    .SS           (SS           ),
    .SPE          (SPE          ),
    .MSTR         (MSTR         ),
    .Reg_write_en (Reg_write_en ),
    .Shifter_en   (shifter_en   ),
    .idle         (idle         ),
    .M_BaudRate   (M_BaudRate   ),
    .SPIF         (SPISR_in     ),
    .BRG_clr      (BRG_clr      ),
    .SPDR_wr_en   (SPDR_wr_en   ),
    .SPDR_rd_en   (SPDR_rd_en   )
);


//______________________________________________________________________________

Port_control_logic u_Port_control_logic(
    .MSTR      (MSTR      ),
    .SCK_out   (SCK_out   ),
    .Data_out  (Data_out  ),
    .SS_master (SS_master ),
    .MOSI      (MOSI      ),
    .MISO      (MISO      ),
    .SCK       (SCK       ),
    .SS        (SS        ),
    .SS_slave  (SS_slave  ),
    .SCK_in    (SCK_in    ),
    .Data_in   (Data_in   )
);

//______________________________________________________________________________

SCK_control u_SCK_control(
    .M_BaudRate (M_BaudRate ),
    .CPOL       (CPOL       ),
    .CPHA       (CPHA       ),
    .idle       (idle       ),
    .SCK_out    (SCK_out    ),
    .Shift_clk  (Shift_clk  ),
    .Sample_clk (Sample_clk )
);

//______________________________________________________________________________

SPCR u_SPCR(
    .SPCR_in (SPCR_in ),
    .clk     (clk     ),
    .rst     (rst     ),
    .SPE     (SPE     ),
    .MSTR    (MSTR    ),
    .CPOL    (CPOL    ),
    .CPHA    (CPHA    ),
    .LSBFE   (LSBFE   )
);
//______________________________________________________________________________
SPISR u_SPISR(
    .clk      (clk      ),
    .rst      (rst      ),
    .en       (Reg_write_en),
    .SPISR_in (SPISR_in ),
    .SPIF     (SPIF     )
);
//______________________________________________________________________________
SPIBR u_SPIBR(
    .SPIBR_in (SPIBR_in ),
    .clk      (clk      ),
    .rst      (rst      ),
    .SPR      (SPR      )
);
//______________________________________________________________________________

SPDR u_SPDR(
    .SPDR_in  (SPDR_out  ),
    .clk      (clk      ),
    .rst      (rst      ),
    .en       (SPDR_wr_en),
    .SPDR_out (SPDR_in ),
    .SPDR_From_user(SPDR_From_user),
    .SPDR_rd_en(SPDR_rd_en)
);



endmodule

TestBench/TestBench.v
`default_nettype none
`timescale 1ns/100ps
`include "SPI_TOP.v"
module SPI_TB;
    reg rst, clk = 0, SS_master, LSBFE, SPISR_in, SPTEF;
    wire SS, MISO, MOSI, SCK;
    reg SS_reg, MISO_reg, MOSI_reg, SCK_reg;
    wire SCK_in, SS_slave, SPIF;
    reg [7:0] SPCR_in, SPIBR_in, SPDR_From_user;
    

    SPI_TOP DUT(
        .rst       (rst       ),
        .SS        (SS        ),
        .MOSI      (MOSI      ),
        .MISO      (MISO      ),
        .SCK       (SCK       ),
        .clk       (clk       ),
        .SS_master (SS_master ),
        .SS_slave  (SS_slave  ),
        .SCK_in    (SCK_in    ),
        .SPCR_in   (SPCR_in   ),
        .LSBFE     (LSBFE     ),
        .SPDR_From_user (SPDR_From_user),
        .SPIF  (SPIF  ),
        .SPIBR_in (SPIBR_in)
    );

    always #5 clk = ~clk;
   // assign SS = SS_reg;
  //  always @(*) begin
    //    if (SPIF)   SPCR_in = 8'bx0x100xx;
   //        end
    assign MISO = 0;
    initial begin
        $dumpfile("dump.vcd");
        $dumpvars;
        rst = 0; #5 rst = 1; SPCR_in = 8'bx0x100xx; SS_master = 0;
        #10;
        SPDR_From_user = 8'b10101010;
        SPIBR_in = 0;
        SPCR_in = 8'bx1x100xx;
        #200;
        SPDR_From_user = 8'hFF;
        #200;
       // SPCR_in = 8'bx0x100xx;
        $finish;

    end

endmodule

TestBench/dump.vcd
$date
	Sat Jul 22 17:10:28 2023
$end
$version
	Icarus Verilog
$end
$timescale
	100ps
$end
$scope module SPI_TB $end
$var wire 1 ! MISO $end
$var wire 1 " SS_slave $end
$var wire 1 # SS $end
$var wire 1 $ SPIF $end
$var wire 1 % SCK_in $end
$var wire 1 & SCK $end
$var wire 1 ' MOSI $end
$var reg 1 ( LSBFE $end
$var reg 8 ) SPCR_in [7:0] $end
$var reg 8 * SPDR_From_user [7:0] $end
$var reg 8 + SPIBR_in [7:0] $end
$var reg 1 , SS_master $end
$var reg 1 - clk $end
$var reg 1 . rst $end
$scope module DUT $end
$var wire 1 / LSBFE $end
$var wire 1 ! MISO $end
$var wire 8 0 SPCR_in [7:0] $end
$var wire 8 1 SPDR_From_user [7:0] $end
$var wire 8 2 SPIBR_in [7:0] $end
$var wire 1 , SS_master $end
$var wire 1 - clk $end
$var wire 1 . rst $end
$var wire 1 3 shifter_en $end
$var wire 1 4 idle $end
$var wire 1 5 Shift_clk $end
$var wire 1 6 Sample_clk $end
$var wire 1 " SS_slave $end
$var wire 1 # SS $end
$var wire 3 7 SPR [2:0] $end
$var wire 1 8 SPISR_in $end
$var wire 1 $ SPIF $end
$var wire 1 9 SPE $end
$var wire 1 : SPDR_wr_en $end
$var wire 1 ; SPDR_rd_en $end
$var wire 8 < SPDR_out [7:0] $end
$var wire 8 = SPDR_in [7:0] $end
$var wire 1 > SCK_out $end
$var wire 1 % SCK_in $end
$var wire 1 & SCK $end
$var wire 1 ? Reg_write_en $end
$var wire 1 @ M_BaudRate $end
$var wire 1 A MSTR $end
$var wire 1 ' MOSI $end
$var wire 1 B Data_out $end
$var wire 1 C Data_in $end
$var wire 1 D CPOL $end
$var wire 1 E CPHA $end
$var wire 1 F BaudRate $end
$var wire 1 G BRG_clr $end
$var parameter 32 H PrescalarWidth $end
$scope module u_BRG $end
$var wire 1 - clk $end
$var wire 1 . rst $end
$var wire 8 I counterNext [7:0] $end
$var wire 1 G clr $end
$var wire 3 J SPR [2:0] $end
$var wire 1 F BaudRate $end
$var parameter 32 K PrescalarWidth $end
$var reg 8 L counter [7:0] $end
$upscope $end
$scope module u_Master_controller $end
$var wire 1 G BRG_clr $end
$var wire 1 F BaudRate $end
$var wire 1 @ M_BaudRate $end
$var wire 1 . rst $end
$var wire 1 # SS $end
$var wire 1 9 SPE $end
$var wire 1 A MSTR $end
$var parameter 32 M Idle $end
$var parameter 32 N Run $end
$var parameter 32 O Update $end
$var reg 1 ? Reg_write_en $end
$var reg 1 ; SPDR_rd_en $end
$var reg 1 : SPDR_wr_en $end
$var reg 1 8 SPIF $end
$var reg 1 3 Shifter_en $end
$var reg 3 P counter [2:0] $end
$var reg 1 Q counter_enable $end
$var reg 2 R current_state [1:0] $end
$var reg 1 4 idle $end
$var reg 2 S next_state [1:0] $end
$upscope $end
$scope module u_Port_control_logic $end
$var wire 1 ! MISO $end
$var wire 1 , SS_master $end
$var wire 1 " SS_slave $end
$var wire 1 # SS $end
$var wire 1 > SCK_out $end
$var wire 1 % SCK_in $end
$var wire 1 & SCK $end
$var wire 1 A MSTR $end
$var wire 1 ' MOSI $end
$var wire 1 B Data_out $end
$var wire 1 C Data_in $end
$upscope $end
$scope module u_SCK_control $end
$var wire 1 @ M_BaudRate $end
$var wire 1 4 idle $end
$var wire 1 D CPOL $end
$var wire 1 E CPHA $end
$var reg 1 > SCK_out $end
$var reg 1 6 Sample_clk $end
$var reg 1 5 Shift_clk $end
$upscope $end
$scope module u_SPCR $end
$var wire 8 T SPCR_in [7:0] $end
$var wire 1 - clk $end
$var wire 1 . rst $end
$var reg 1 E CPHA $end
$var reg 1 D CPOL $end
$var reg 1 U LSBFE $end
$var reg 1 A MSTR $end
$var reg 1 9 SPE $end
$upscope $end
$scope module u_SPDR $end
$var wire 8 V SPDR_From_user [7:0] $end
$var wire 8 W SPDR_out [7:0] $end
$var wire 1 ; SPDR_rd_en $end
$var wire 1 - clk $end
$var wire 1 : en $end
$var wire 1 . rst $end
$var wire 8 X SPDR_in [7:0] $end
$var reg 8 Y SPDR [7:0] $end
$upscope $end
$scope module u_SPIBR $end
$var wire 8 Z SPIBR_in [7:0] $end
$var wire 1 - clk $end
$var wire 1 . rst $end
$var wire 3 [ SPR [2:0] $end
$var reg 1 \ SPR0 $end
$var reg 1 ] SPR1 $end
$var reg 1 ^ SPR2 $end
$upscope $end
$scope module u_SPISR $end
$var wire 1 8 SPISR_in $end
$var wire 1 - clk $end
$var wire 1 ? en $end
$var wire 1 . rst $end
$var reg 1 $ SPIF $end
$upscope $end
$scope module u_Shifter $end
$var wire 1 C Data_in $end
$var wire 8 _ SPDR_in [7:0] $end
$var wire 1 ; SPDR_rd_en $end
$var wire 1 : SPDR_wr_en $end
$var wire 1 6 Sample_clk $end
$var wire 1 5 Shift_clk $end
$var wire 1 3 shifter_en $end
$var parameter 32 ` DWIDTH $end
$var reg 1 B Data_out $end
$var reg 8 a SPDR_out [7:0] $end
$var reg 8 b shifter_data [7:0] $end
$var reg 8 c shifter_data_reg [7:0] $end
$upscope $end
$upscope $end
$upscope $end
$enddefinitions $end
$comment Show the parameter values. $end
$dumpall
b1000 `
b10 O
b1 N
b0 M
b11 K
b11 H
$end
#0
$dumpvars
b0 c
b0 b
bz a
b0 _
0^
1]
0\
b10 [
bx Z
b0 Y
bz X
b0 W
bx V
0U
bx T
b0 S
b0 R
0Q
b0 P
b0 L
b10 J
b1 I
1G
0F
0E
0D
zC
xB
0A
0@
0?
0>
b0 =
bz <
1;
0:
09
08
b10 7
06
05
14
03
bx 2
bx 1
bx 0
x/
0.
0-
x,
bx +
bx *
bx )
x(
z'
z&
z%
0$
z#
z"
x!
$end
#50
0!
bx b
bx c
0&
0#
0C
x'
bx =
bx W
bx _
bx Y
x^
x]
xF
bx 7
bx J
bx [
x\
xU
1A
0,
bx0x100xx )
bx0x100xx 0
bx0x100xx T
1.
1-
#100
0-
#150
0G
b1 S
b10101010 b
b10101010 c
19
0F
0^
0]
b0 7
b0 J
b0 [
0\
b10101010 =
b10101010 W
b10101010 _
b10101010 Y
1-
bx1x100xx )
bx1x100xx 0
bx1x100xx T
b0 +
b0 2
b0 Z
b10101010 *
b10101010 1
b10101010 V
#200
0-
#250
1'
1B
15
1Q
13
0;
04
b1 R
b10 I
1F
b1 L
1-
#300
0-
#350
b1010100 b
b1010100 c
1&
1>
16
05
1@
b11 I
0F
b10 L
1-
#400
0-
#450
0'
0B
b1 P
0&
0>
06
15
0@
b100 I
1F
b11 L
1-
#500
0-
#550
b10101000 b
b10101000 c
1&
1>
16
05
1@
b101 I
0F
b100 L
1-
#600
0-
#650
1'
1B
b10 P
0&
0>
06
15
0@
b110 I
1F
b101 L
1-
#700
0-
#750
b1010000 b
b1010000 c
1&
1>
16
05
1@
b111 I
0F
b110 L
1-
#800
0-
#850
0'
0B
b11 P
0&
0>
06
15
0@
b1000 I
1F
b111 L
1-
#900
0-
#950
b10100000 b
b10100000 c
1&
1>
16
05
1@
b1001 I
0F
b1000 L
1-
#1000
0-
#1050
1'
1B
b100 P
0&
0>
06
15
0@
b1010 I
1F
b1001 L
1-
#1100
0-
#1150
b1000000 b
b1000000 c
1&
1>
16
05
1@
b1011 I
0F
b1010 L
1-
#1200
0-
#1250
0'
0B
b101 P
0&
0>
06
15
0@
b1100 I
1F
b1011 L
1-
#1300
0-
#1350
b10000000 b
b10000000 c
1&
1>
16
05
1@
b1101 I
0F
b1100 L
1-
#1400
0-
#1450
1'
1B
b110 P
0&
0>
06
15
0@
b1110 I
1F
b1101 L
1-
#1500
0-
#1550
b0 b
b0 c
1&
1>
16
05
1@
b1111 I
0F
b1110 L
1-
#1600
0-
#1650
0'
b10 S
0B
b111 P
0&
0>
06
15
0@
b10000 I
1F
b1111 L
1-
#1700
0-
#1750
1&
1>
16
05
1@
b10001 I
0F
b10000 L
1-
#1800
0-
#1850
b0 <
b0 X
b0 a
1?
18
1:
14
0Q
03
b0 S
b0 P
b10 R
0&
0>
06
05
0@
b10010 I
1F
b10001 L
1-
#1900
0-
#1950
1$
b0 =
b0 W
b0 _
b0 Y
b10011 I
0F
b10010 L
1-
#2000
0-
#2050
bz <
bz X
bz a
1;
0?
08
0:
14
b1 S
b0 R
b10100 I
1F
b10011 L
1-
#2100
0-
#2150
b11111111 b
b11111111 c
b11111111 =
b11111111 W
b11111111 _
b11111111 Y
b10101 I
0F
b10100 L
1-
b11111111 *
b11111111 1
b11111111 V
#2200
0-
#2250
1'
1B
15
1Q
13
0;
04
b1 R
b10110 I
1F
b10101 L
1-
#2300
0-
#2350
b11111110 b
b11111110 c
1&
1>
16
05
1@
b10111 I
0F
b10110 L
1-
#2400
0-
#2450
b1 P
0&
0>
06
15
0@
b11000 I
1F
b10111 L
1-
#2500
0-
#2550
b11111100 b
b11111100 c
1&
1>
16
05
1@
b11001 I
0F
b11000 L
1-
#2600
0-
#2650
b10 P
0&
0>
06
15
0@
b11010 I
1F
b11001 L
1-
#2700
0-
#2750
b11111000 b
b11111000 c
1&
1>
16
05
1@
b11011 I
0F
b11010 L
1-
#2800
0-
#2850
b11 P
0&
0>
06
15
0@
b11100 I
1F
b11011 L
1-
#2900
0-
#2950
b11110000 b
b11110000 c
1&
1>
16
05
1@
b11101 I
0F
b11100 L
1-
#3000
0-
#3050
b100 P
0&
0>
06
15
0@
b11110 I
1F
b11101 L
1-
#3100
0-
#3150
b11100000 b
b11100000 c
1&
1>
16
05
1@
b11111 I
0F
b11110 L
1-
#3200
0-
#3250
b101 P
0&
0>
06
15
0@
b100000 I
1F
b11111 L
1-
#3300
0-
#3350
b11000000 b
b11000000 c
1&
1>
16
05
1@
b100001 I
0F
b100000 L
1-
#3400
0-
#3450
b110 P
0&
0>
06
15
0@
b100010 I
1F
b100001 L
1-
#3500
0-
#3550
b10000000 b
b10000000 c
1&
1>
16
05
1@
b100011 I
0F
b100010 L
1-
#3600
0-
#3650
b10 S
b111 P
0&
0>
06
15
0@
b100100 I
1F
b100011 L
1-
#3700
0-
#3750
b0 b
b0 c
1&
1>
16
05
1@
b100101 I
0F
b100100 L
1-
#3800
0-
#3850
b0 <
b0 X
b0 a
0'
1?
18
1:
14
0Q
03
b0 S
0B
b0 P
b10 R
0&
0>
06
05
0@
b100110 I
1F
b100101 L
1-
#3900
0-
#3950
b0 =
b0 W
b0 _
b0 Y
b100111 I
0F
b100110 L
1-
#4000
0-
#4050
bz <
bz X
bz a
1;
0?
08
0:
14
b1 S
b0 R
b101000 I
1F
b100111 L
1-
#4100
0-
#4150
b11111111 b
b11111111 c
b11111111 =
b11111111 W
b11111111 _
b11111111 Y
b101001 I
0F
b101000 L
1-
